MANIFEST.in
README.rst
setup.py
docs/HISTORY.txt
docs/INSTALL.txt
docs/LICENSE.GPL
docs/LICENSE.txt
docs/TODO.txt
unice/.DS_Store
unice/__init__.py
unice.portlet.telechargement.egg-info/PKG-INFO
unice.portlet.telechargement.egg-info/SOURCES.txt
unice.portlet.telechargement.egg-info/dependency_links.txt
unice.portlet.telechargement.egg-info/entry_points.txt
unice.portlet.telechargement.egg-info/namespace_packages.txt
unice.portlet.telechargement.egg-info/not-zip-safe
unice.portlet.telechargement.egg-info/requires.txt
unice.portlet.telechargement.egg-info/top_level.txt
unice/portlet/.DS_Store
unice/portlet/__init__.py
unice/portlet/telechargement/__init__.py
unice/portlet/telechargement/configure.zcml
unice/portlet/telechargement/telechargementportlet.pt
unice/portlet/telechargement/telechargementportlet.py
unice/portlet/telechargement/vocabularies.py
unice/portlet/telechargement/browser/.DS_Store
unice/portlet/telechargement/browser/__init__.py
unice/portlet/telechargement/browser/configure.zcml
unice/portlet/telechargement/browser/stylesheets/styles.css
unice/portlet/telechargement/profiles/.DS_Store
unice/portlet/telechargement/profiles/default/cssregistry.xml
unice/portlet/telechargement/profiles/default/metadata.xml
unice/portlet/telechargement/profiles/default/portlets.xml
unice/portlet/telechargement/tests/__init__.py
unice/portlet/telechargement/tests/base.py
unice/portlet/telechargement/tests/test_portlet.py